lab1/fpga/VCB4Re.v
module VCB4RE(ce, Q, sys_clk, TC, R, CEO);

input ce;
output reg [3:0] Q = 0;
input sys_clk;
output wire TC;
input R;
output wire CEO;

assign TC = (Q == 15);
assign CEO = ce & TC;

always @(posedge sys_clk)
begin
        Q <= R ? 0 : ce ? Q + 1 : Q;
end

endmodule

lab1/fpga/VCB4Re_tb.v
module test;

initial
begin
     $dumpfile("VCB4Re.vcd");
     $dumpvars(0,test);
     # 31 $finish;
end

reg clk = 0;
wire [3:0] out;
reg R = 0;
reg ce = 1;
wire TC;
wire CEO;
VCB4RE counter (ce, out, clk, TC, R, CEO);

always #1
begin
        clk = !clk;
        $monitor("Time step %t, clk = %0d, out = 0x%h, TC = 0x%h, CEO = 0x%h",
                 $stime, clk, out, TC, CEO);
end

endmodule

lab1/fpga/VCB4Re.vcd
$date
	Thu Feb 22 01:20:17 2018
$end
$version
	Icarus Verilog
$end
$timescale
	1s
$end
$scope module test $end
$var wire 4 ! out [3:0] $end
$var wire 1 " TC $end
$var wire 1 # CEO $end
$var reg 1 $ R $end
$var reg 1 % ce $end
$var reg 1 & clk $end
$scope module counter $end
$var wire 1 # CEO $end
$var wire 1 $ R $end
$var wire 1 % ce $end
$var wire 1 & sys_clk $end
$var wire 1 " TC $end
$var reg 4 ' Q [3:0] $end
$upscope $end
$upscope $end
$enddefinitions $end
#0
$dumpvars
b0 '
0&
1%
0$
0#
0"
b0 !
$end
#1
b1 !
b1 '
1&
#2
0&
#3
b10 !
b10 '
1&
#4
0&
#5
b11 !
b11 '
1&
#6
0&
#7
b100 !
b100 '
1&
#8
0&
#9
b101 !
b101 '
1&
#10
0&
#11
b110 !
b110 '
1&
#12
0&
#13
b111 !
b111 '
1&
#14
0&
#15
b1000 !
b1000 '
1&
#16
0&
#17
b1001 !
b1001 '
1&
#18
0&
#19
b1010 !
b1010 '
1&
#20
0&
#21
b1011 !
b1011 '
1&
#22
0&
#23
b1100 !
b1100 '
1&
#24
0&
#25
b1101 !
b1101 '
1&
#26
0&
#27
b1110 !
b1110 '
1&
#28
0&
#29
1#
1"
b1111 !
b1111 '
1&
#30
0&
#31
0#
0"
b0 !
b0 '
1&
