lab1/fpga/VCBDmSE.v
module VCBDmSE(ce, Q, sys_clk, TC, s, CEO);

input ce;
output reg [3:0] Q = 0;
input sys_clk;
output wire TC;
input s;
output wire CEO;

assign TC = (Q == 0);
assign CEO = ce & TC;

always @(posedge sys_clk)
begin
        Q <= s ? 15 : ce ? Q - 1 : Q;
end

endmodule

lab1/fpga/VCBDmSE_tb.v
module test;

initial
begin
     $dumpfile("VCBDmSE.vcd");
     $dumpvars(0, test);
     # 32 $finish;
end

reg clk = 0;
wire [3:0] out;
reg s = 0;
reg ce = 1;
wire TC;
wire CEO;
VCBDmSE counter (ce, out, clk, TC, s, CEO);

always #1
begin
        clk = !clk;
        $monitor("Time step %t, clk = %0d, out = 0x%h, TC = 0x%h, CEO = 0x%h",
                 $stime, clk, out, TC, CEO);
end

endmodule

lab1/fpga/VCBDmSE.vcd
$date
	Thu Feb 22 02:01:45 2018
$end
$version
	Icarus Verilog
$end
$timescale
	1s
$end
$scope module test $end
$var wire 4 ! out [3:0] $end
$var wire 1 " TC $end
$var wire 1 # CEO $end
$var reg 1 $ ce $end
$var reg 1 % clk $end
$var reg 1 & s $end
$scope module counter $end
$var wire 1 # CEO $end
$var wire 1 $ ce $end
$var wire 1 & s $end
$var wire 1 % sys_clk $end
$var wire 1 " TC $end
$var reg 4 ' Q [3:0] $end
$upscope $end
$upscope $end
$enddefinitions $end
#0
$dumpvars
b0 '
0&
0%
1$
1#
1"
b0 !
$end
#1
0#
0"
b1111 !
b1111 '
1%
#2
0%
#3
b1110 !
b1110 '
1%
#4
0%
#5
b1101 !
b1101 '
1%
#6
0%
#7
b1100 !
b1100 '
1%
#8
0%
#9
b1011 !
b1011 '
1%
#10
0%
#11
b1010 !
b1010 '
1%
#12
0%
#13
b1001 !
b1001 '
1%
#14
0%
#15
b1000 !
b1000 '
1%
#16
0%
#17
b111 !
b111 '
1%
#18
0%
#19
b110 !
b110 '
1%
#20
0%
#21
b101 !
b101 '
1%
#22
0%
#23
b100 !
b100 '
1%
#24
0%
#25
b11 !
b11 '
1%
#26
0%
#27
b10 !
b10 '
1%
#28
0%
#29
b1 !
b1 '
1%
#30
0%
#31
1#
1"
b0 !
b0 '
1%
