lab2/fpga/spi_transceiver.v
/*
 * The SPI module hardcoded to SPI mode 0:
 *      CPOL = 0;
 *      CPHA = 0;
 */
module spi_transceiver
#(
        parameter SPI_SPEED_HZ = 8_000_000
) (
        input            i_sys_clk,
        input [7:0]      i_byte,
        input            i_activate,
        input            i_spi_miso,
        output reg       o_byte_done,
        output reg [7:0] o_byte,
        output reg       o_spi_sck = 1'b0,
        output reg       o_spi_mosi = 1'b0
);

localparam SPI_EDGE_CYCLES = 50_000_000/SPI_SPEED_HZ;

localparam spi_IDLE             = 4'b0000;
localparam spi_PRERAISE_SCK     = 4'b0001;
localparam spi_RAISE_SCK        = 4'b0010;
localparam spi_POSTRAISE_SCK    = 4'b0011;
localparam spi_NOTIFY           = 4'b0100;

reg [4:0] transmitter_state = spi_IDLE;
reg [15:0] spi_cycles = 16'b0;
reg [2:0]  spi_bit    = 3'd7;
reg [7:0]  spi_data   = 8'b0;
reg activate_idle     = 1'b0;
reg [7:0] spi_out_reg = 8'b0;
reg miso_pin0         = 1'b0;
reg spi_miso          = 1'b0;

//It addresses problems caused by metastability
always @(posedge i_sys_clk)
begin
        miso_pin0 <= i_spi_miso;
        spi_miso <= miso_pin0;
end

always @(posedge i_sys_clk)
begin
        $display("Current state %b %d", transmitter_state, o_spi_mosi);
        case (transmitter_state)
        spi_IDLE:
        begin
                spi_cycles <= 16'b0;
                spi_bit <= 3'd7;
                o_byte_done <= 1'b0;

                if (i_activate != activate_idle)
                begin
                        spi_data <= i_byte;
                        transmitter_state <= spi_PRERAISE_SCK;
                        o_spi_sck <= 1'b0;
                end
        end
        spi_PRERAISE_SCK:
        begin
                if (spi_cycles < SPI_EDGE_CYCLES / 2)
                begin
                        o_spi_mosi <= spi_data[spi_bit];
                        o_spi_sck <= 1'b0;
                        spi_cycles <= spi_cycles + 16'b1;
                end
                else
                        transmitter_state <= spi_RAISE_SCK;
        end
        spi_RAISE_SCK:
        begin
                if (spi_cycles == (SPI_EDGE_CYCLES / 2))
                begin
                        o_spi_sck <= 1'b1;
                        spi_out_reg[spi_bit] <= spi_miso;
                        spi_cycles <= spi_cycles + 16'b1;
                end
                else
                        transmitter_state <= spi_POSTRAISE_SCK;
        end
        spi_POSTRAISE_SCK:
        begin
                if (spi_cycles == SPI_EDGE_CYCLES - 1)
                begin
                        spi_cycles <= 16'b0;
                        if (spi_bit == 3'd0)
                                transmitter_state <= spi_NOTIFY;
                        else
                        begin
                                spi_bit <= spi_bit - 3'b1;
                                transmitter_state <= spi_PRERAISE_SCK;
                        end
                        o_spi_sck <= 1'b0;
                end
                else
                        spi_cycles <= spi_cycles + 16'b1;
        end
        spi_NOTIFY:
        begin
                activate_idle <= ~activate_idle;
                o_byte_done <= 1'b1;
                transmitter_state <= spi_IDLE;
                o_byte <= spi_out_reg;
        end
        endcase
end

endmodule

lab2/fpga/spi_tb.v
module test;

initial
begin
        $dumpfile("spi.vcd");
        $dumpvars(0,test);
        # 2 spi_switch = ~spi_switch;
        # 0 spi_tx_byte = 8'hF0;
        # 120 $finish;
end

reg  clk = 0;
reg  [7:0] spi_tx_byte = 8'hF0;
reg  spi_switch = 1'b0;
reg i_spi_miso = 1'b0;
wire spi_tx_done;
wire [7:0] spi_rx_byte;
wire o_spi_sck;
wire o_spi_mosi;

always #1
begin
        clk = !clk;
        $monitor("Time step %t, clk = %d, spi_byte_next = 0x%h, spi_switch = %d, spi_sck = %d, spi_mosi = %d, spi_done = %d",
                 $stime, clk, spi_tx_byte, spi_switch, o_spi_sck, o_spi_mosi, spi_tx_done);
end

spi_transceiver #(.SPI_SPEED_HZ(12_000_000)) spi_rxtx(
        .i_sys_clk(clk),
        .i_byte(spi_tx_byte),
        .i_activate(spi_switch),
        .i_spi_miso(i_spi_miso),
        .o_byte_done(spi_tx_done),
        .o_byte(spi_rx_byte),
        .o_spi_sck(o_spi_sck),
        .o_spi_mosi(o_spi_mosi));

endmodule

lab2/fpga/spi.vcd
$date
	Sun May  6 04:52:12 2018
$end
$version
	Icarus Verilog
$end
$timescale
	1s
$end
$scope module test $end
$var wire 1 ! spi_tx_done $end
$var wire 8 " spi_rx_byte [7:0] $end
$var wire 1 # o_spi_sck $end
$var wire 1 $ o_spi_mosi $end
$var reg 1 % clk $end
$var reg 1 & i_spi_miso $end
$var reg 1 ' spi_switch $end
$var reg 8 ( spi_tx_byte [7:0] $end
$scope module spi_rxtx $end
$var wire 1 ' i_activate $end
$var wire 8 ) i_byte [7:0] $end
$var wire 1 & i_spi_miso $end
$var wire 1 % i_sys_clk $end
$var reg 1 * activate_idle $end
$var reg 1 + miso_pin0 $end
$var reg 8 , o_byte [7:0] $end
$var reg 1 ! o_byte_done $end
$var reg 1 $ o_spi_mosi $end
$var reg 1 # o_spi_sck $end
$var reg 3 - spi_bit [2:0] $end
$var reg 16 . spi_cycles [15:0] $end
$var reg 8 / spi_data [7:0] $end
$var reg 1 0 spi_miso $end
$var reg 8 1 spi_out_reg [7:0] $end
$var reg 5 2 transmitter_state [4:0] $end
$upscope $end
$upscope $end
$enddefinitions $end
#0
$dumpvars
b0 2
b0 1
00
b0 /
b0 .
b111 -
bx ,
0+
0*
b11110000 )
b11110000 (
0'
0&
0%
0$
0#
bx "
x!
$end
#1
0!
1%
#2
0%
1'
#3
b1 2
b11110000 /
1%
#4
0%
#5
b1 .
1$
1%
#6
0%
#7
b10 .
1%
#8
0%
#9
b10 2
1%
#10
0%
#11
b11 .
1#
1%
#12
0%
#13
b11 2
1%
#14
0%
#15
0#
b1 2
b110 -
b0 .
1%
#16
0%
#17
b1 .
1%
#18
0%
#19
b10 .
1%
#20
0%
#21
b10 2
1%
#22
0%
#23
b11 .
1#
1%
#24
0%
#25
b11 2
1%
#26
0%
#27
0#
b1 2
b101 -
b0 .
1%
#28
0%
#29
b1 .
1%
#30
0%
#31
b10 .
1%
#32
0%
#33
b10 2
1%
#34
0%
#35
b11 .
1#
1%
#36
0%
#37
b11 2
1%
#38
0%
#39
0#
b1 2
b100 -
b0 .
1%
#40
0%
#41
b1 .
1%
#42
0%
#43
b10 .
1%
#44
0%
#45
b10 2
1%
#46
0%
#47
b11 .
1#
1%
#48
0%
#49
b11 2
1%
#50
0%
#51
0#
b1 2
b11 -
b0 .
1%
#52
0%
#53
b1 .
0$
1%
#54
0%
#55
b10 .
1%
#56
0%
#57
b10 2
1%
#58
0%
#59
b11 .
1#
1%
#60
0%
#61
b11 2
1%
#62
0%
#63
0#
b1 2
b10 -
b0 .
1%
#64
0%
#65
b1 .
1%
#66
0%
#67
b10 .
1%
#68
0%
#69
b10 2
1%
#70
0%
#71
b11 .
1#
1%
#72
0%
#73
b11 2
1%
#74
0%
#75
0#
b1 2
b1 -
b0 .
1%
#76
0%
#77
b1 .
1%
#78
0%
#79
b10 .
1%
#80
0%
#81
b10 2
1%
#82
0%
#83
b11 .
1#
1%
#84
0%
#85
b11 2
1%
#86
0%
#87
0#
b1 2
b0 -
b0 .
1%
#88
0%
#89
b1 .
1%
#90
0%
#91
b10 .
1%
#92
0%
#93
b10 2
1%
#94
0%
#95
b11 .
1#
1%
#96
0%
#97
b11 2
1%
#98
0%
#99
0#
b100 2
b0 .
1%
#100
0%
#101
b0 "
b0 ,
b0 2
1!
1*
1%
#102
0%
#103
0!
b111 -
1%
